filtered_intervaltree-0.0.7.dist-info/DESCRIPTION.rst
filtered_intervaltree-0.0.7.dist-info/METADATA
filtered_intervaltree-0.0.7.dist-info/RECORD
filtered_intervaltree-0.0.7.dist-info/WHEEL
filtered_intervaltree-0.0.7.dist-info/metadata.json
filtered_intervaltree-0.0.7.dist-info/top_level.txt
intervaltree/__init__.py
intervaltree/bs_tree.py
intervaltree/bs_tree_funcs.py
intervaltree/bs_tree_node.py
intervaltree/easy_hashes.py
intervaltree/i_tree_funcs.py
intervaltree/interval.py
intervaltree/print_tree.py
intervaltree/rb_tree.py
intervaltree/rb_tree_funcs.py
intervaltree/rb_tree_node.py
