Metadata-Version: 2.0
Name: filtered-intervaltree
Version: 0.0.7
Summary: an intervaltree with early exit bloom filters
Home-page: https://github.com/lostinplace/filtered-intervaltree
Author: cwheeler
Author-email: cmwhee@gmail.com
License: MIT
Keywords: rbtree intervaltree bloomfilter
Platform: UNKNOWN
Classifier: Development Status :: 3 - Alpha
Classifier: Intended Audience :: Developers
Classifier: Topic :: Software Development :: Libraries
Classifier: License :: OSI Approved :: MIT License
Classifier: Programming Language :: Python :: 3.5
Requires-Dist: coverage (==4.0.3)
Requires-Dist: mmh3 (==2.3.1)
Requires-Dist: numpy (==1.11.0)
Requires-Dist: py (==1.4.31)
Requires-Dist: pytest (==2.9.1)
Requires-Dist: termcolor (==1.1.0)
Provides-Extra: test
Requires-Dist: coverage; extra == 'test'
